fleks/__init__.py
fleks/__main__.py
fleks/_version.py
fleks/config.py
fleks/constants.py
fleks/models.py
fleks/plugin.py
fleks/app/__init__.py
fleks/cli/__init__.py
fleks/cli/arguments.py
fleks/cli/click.py
fleks/cli/options.py
fleks/cli/root_group.py
fleks/meta/__init__.py
fleks/meta/namespace.py
fleks/meta/oop.py
fleks/util/__init__.py
fleks/util/click.py
fleks/util/console.py
fleks/util/lme.py
fleks/util/tagging.py
fleks/util/typing.py
fleks-2025.8.6.4.1.dist-info/METADATA
fleks-2025.8.6.4.1.dist-info/WHEEL
fleks-2025.8.6.4.1.dist-info/top_level.txt
fleks-2025.8.6.4.1.dist-info/RECORD
