Metadata-Version: 2.4
Name: fleks
Version: 2025.8.6.4.1
Summary: Python application framework
Home-page: https://github.com/elo-enterprises/fleks/
Author: elo
License: MIT
Project-URL: Documentation, https://github.com/elo-enterprises/fleks/
Project-URL: Source, https://github.com/elo-enterprises/fleks/
Project-URL: Download, https://github.com/elo-enterprises/fleks/#files
Platform: any
Classifier: Programming Language :: Python
Requires-Python: >3.7
Requires-Dist: pydash==7.0.1
Requires-Dist: memoized-property==1.0.3
Requires-Dist: pydantic>=2
Requires-Dist: blinker==1.6.2
Requires-Dist: rich>=13.3.4
Requires-Dist: click>=8.1.4
Requires-Dist: enlighten==1.11.2
Provides-Extra: dev
Requires-Dist: IPython; extra == "dev"
Provides-Extra: testing
Requires-Dist: IPython; extra == "testing"
Requires-Dist: tox; extra == "testing"
Requires-Dist: pytest; extra == "testing"
Requires-Dist: pytest-cov; extra == "testing"
Requires-Dist: mock; extra == "testing"
Requires-Dist: flake8==5.0.4; extra == "testing"
Provides-Extra: lint
Requires-Dist: tox; extra == "lint"
Provides-Extra: publish
Requires-Dist: twine; extra == "publish"
